yggpeer/__init__.py
yggpeer/peer_manager.py
yggpeer-0.1.1.dist-info/LICENSE
yggpeer-0.1.1.dist-info/METADATA
yggpeer-0.1.1.dist-info/WHEEL
yggpeer-0.1.1.dist-info/top_level.txt
yggpeer-0.1.1.dist-info/RECORD
