Metadata-Version: 2.1
Name: yggpeer
Version: 0.1.1
Summary: Peer-to-peer communication library over Yggdrasil
Home-page: https://github.com/immartian/yggpeer
Author: Isaac Mao
Author-email: im@here.news
Classifier: Programming Language :: Python :: 3
Classifier: License :: OSI Approved :: MIT License
Classifier: Operating System :: OS Independent
Requires-Python: >=3.6
License-File: LICENSE
